{
  "version": "v846",
  "timestamp": "2026-06-29T04:13:03.719222",
  "passed": 15,
  "total": 15,
  "pass_rate": 100.0,
  "marginal_duality": 4.93002,
  "cc_set": {
    "str": 310,
    "phy": 110,
    "ind": 120,
    "cri": 3.0
  },
  "berserker": {
    "fixed_total": 9.27,
    "pct_total": 32.81
  },
  "swordsman": {
    "pct_total": 45.7
  },
  "tests": [
    {
      "test": "CC套力量合计",
      "expected": 310,
      "actual": 310,
      "pass": true,
      "status": "✅"
    },
    {
      "test": "CC套物理攻击合计",
      "expected": 110,
      "actual": 110,
      "pass": true,
      "status": "✅"
    },
    {
      "test": "CC套独立攻击合计",
      "expected": 120,
      "actual": 120,
      "pass": true,
      "status": "✅"
    },
    {
      "test": "CC套暴击率合计",
      "expected": 3.0,
      "actual": 3.0,
      "pass": true,
      "status": "✅"
    },
    {
      "test": "狂战士独立攻击收益",
      "expected": 0.08,
      "actual": 0.08,
      "pass": true,
      "status": "✅"
    },
    {
      "test": "狂战士暴击收益",
      "expected": 0.0118,
      "actual": 0.0118,
      "pass": true,
      "status": "✅"
    },
    {
      "test": "狂战士固伤综合",
      "expected": 0.0927,
      "actual": 0.0927,
      "pass": true,
      "status": "✅"
    },
    {
      "test": "狂战士力量收益(暴走后)",
      "expected": 0.2442,
      "actual": 0.2442,
      "pass": true,
      "status": "✅"
    },
    {
      "test": "狂战士物理攻击收益",
      "expected": 0.055,
      "actual": 0.055,
      "pass": true,
      "status": "✅"
    },
    {
      "test": "狂战士百分比综合",
      "expected": 0.3281,
      "actual": 0.3281,
      "pass": true,
      "status": "✅"
    },
    {
      "test": "剑魂力量收益",
      "expected": 0.3647,
      "actual": 0.3647,
      "pass": true,
      "status": "✅"
    },
    {
      "test": "剑魂物理攻击收益",
      "expected": 0.055,
      "actual": 0.055,
      "pass": true,
      "status": "✅"
    },
    {
      "test": "剑魂暴击收益",
      "expected": 0.012,
      "actual": 0.012,
      "pass": true,
      "status": "✅"
    },
    {
      "test": "剑魂百分比综合",
      "expected": 0.457,
      "actual": 0.457,
      "pass": true,
      "status": "✅"
    },
    {
      "test": "边际对偶",
      "expected": 4.93,
      "actual": 4.93,
      "pass": true,
      "status": "✅"
    }
  ]
}