{
  "version": "v2440",
  "timestamp": "2026-07-11 16:15 CST",
  "drift_rounds": 965,
  "passed": 5,
  "total": 7,
  "all_pass": false,
  "checks": [
    {
      "name": "CC属性4/4精确",
      "pass": true
    },
    {
      "name": "固伤9.27%",
      "pass": true
    },
    {
      "name": "百分比32.81%",
      "pass": false
    },
    {
      "name": "剑魂45.70%",
      "pass": false
    },
    {
      "name": "边际对偶4.928934",
      "pass": true
    },
    {
      "name": "破极狂战2743",
      "pass": true
    },
    {
      "name": "破极剑魂2886",
      "pass": true
    }
  ],
  "known_issues": [
    "百分比闭环校验漏洞(公式值与KB值偏差): 狂战士60.26% vs KB 32.81%, 剑魂65.38% vs KB 45.70%"
  ],
  "values": {
    "cc_attrs": {
      "力量": 310,
      "物理攻击": 110,
      "独立攻击": 120,
      "暴击": 3
    },
    "berserker_fixed_damage": 9.27,
    "berserker_percent": 60.26,
    "swordman_percent": 65.38,
    "marginal_parity": 4.928934,
    "berserker_coop_weapon": 2743,
    "swordman_coop_weapon": 2886,
    "framework": "FAAL三阶七维+三级级联+装备三原则+二元分流",
    "self_evolution_boundary": "持续遵守，核心数据零漂移"
  }
}