{
  "version": "v1417",
  "timestamp": "2026-07-04T08:13:00+08:00",
  "test_count": 15,
  "passed": 15,
  "results": {
    "cc_str": 310,
    "cc_phy": 110,
    "cc_ind": 120,
    "cc_crit": 0.03,
    "berserker_ind_gain": 9.6,
    "berserker_crit_gain": 1.18,
    "berserker_fixed_total": 10.89,
    "berserker_str_gain": 24.42,
    "berserker_phy_gain": 5.5,
    "berserker_pct_total": 32.82,
    "swordsman_str_gain": 36.47,
    "swordsman_phy_gain": 4.23,
    "swordsman_total": 43.92,
    "marginal_dual": 1.392868,
    "po_synergy_phy": 2710,
    "berserker_berserk_str": 1019.2,
    "berserker_base_str": 728,
    "swordsman_str_base": 600,
    "swordsman_phy_po": 2600
  },
  "status": "FAAL三阶七维框架固化状态确认，核心数据零漂移"
}