{
  "version": "v1759",
  "timestamp": "2026-07-06 18:18",
  "cc_stats": {
    "力量": 310,
    "物理攻击": 110,
    "独立攻击": 120,
    "暴击": 3.0
  },
  "berserker_fixed_pct": 9.27,
  "berserker_pct": 32.81,
  "swordsman_pct": 58.8,
  "marginal_duality": 3.539371,
  "poe_wpn_attack": 2743.0,
  "total_checks": 9,
  "passed_checks": 7,
  "results": [
    {
      "项目": "CC套力量",
      "计算值": "310",
      "标准值": "310",
      "通过": true,
      "备注": ""
    },
    {
      "项目": "CC套物理攻击",
      "计算值": "110",
      "标准值": "110",
      "通过": true,
      "备注": ""
    },
    {
      "项目": "CC套独立攻击",
      "计算值": "120",
      "标准值": "120",
      "通过": true,
      "备注": ""
    },
    {
      "项目": "CC套暴击",
      "计算值": "3.0",
      "标准值": "3.0",
      "通过": true,
      "备注": ""
    },
    {
      "项目": "狂战士固伤综合",
      "计算值": "9.27%",
      "标准值": "9.27%",
      "通过": true,
      "备注": "独立攻击+7.97% × 暴击系数"
    },
    {
      "项目": "狂战士百分比综合",
      "计算值": "32.81%",
      "标准值": "32.81%",
      "通过": true,
      "备注": "力量+24.39% × 物攻+5.50% × 暴击"
    },
    {
      "项目": "剑魂百分比综合",
      "计算值": "58.80%",
      "标准值": "45.7%",
      "通过": false,
      "备注": "力量+38.13% × 物攻+5.21% × 独立+7.97% × 暴击"
    },
    {
      "项目": "边际对偶(百分比/固伤比)",
      "计算值": "3.539371",
      "标准值": "4.93002",
      "通过": false,
      "备注": "系统固有频率不变量"
    },
    {
      "项目": "破极兵刃协同物攻",
      "计算值": "2743",
      "标准值": "2743",
      "通过": true,
      "备注": "2110×1.30"
    }
  ]
}