{
  "version": "v1516",
  "timestamp": "2026-07-05T00:34:14.096552",
  "checks": 11,
  "passed": 11,
  "rate": "100.0%",
  "results": [
    {
      "check": "CC套力量",
      "expected": 310,
      "actual": 310,
      "status": "✅"
    },
    {
      "check": "CC套物理攻击",
      "expected": 110,
      "actual": 110,
      "status": "✅"
    },
    {
      "check": "CC套独立攻击",
      "expected": 120,
      "actual": 120,
      "status": "✅"
    },
    {
      "check": "CC套暴击率",
      "expected": 3.0,
      "actual": 3.0,
      "status": "✅"
    },
    {
      "check": "狂战士固伤综合",
      "expected": 9.27,
      "actual": 9.27,
      "status": "✅"
    },
    {
      "check": "狂战士百分比综合",
      "expected": 32.81,
      "actual": 32.81,
      "status": "✅"
    },
    {
      "check": "剑魂百分比综合",
      "expected": 45.7,
      "actual": 45.7,
      "status": "✅"
    },
    {
      "check": "边际对偶",
      "expected": 4.93002,
      "actual": 4.93002,
      "status": "✅"
    },
    {
      "check": "破极兵刃协同物攻",
      "expected": 2743,
      "actual": 2743,
      "status": "✅"
    },
    {
      "check": "FAAL三阶七维框架固化",
      "expected": true,
      "actual": true,
      "status": "✅"
    },
    {
      "check": "核心数据零漂移",
      "expected": true,
      "actual": true,
      "status": "✅"
    }
  ],
  "summary": "v1516: 11/11 Python独立验算100%通过"
}